beerbolaget/__init__.py
beerbolaget/beer.py
beerbolaget/common.py
beerbolaget/rating.py
beerbolaget-0.4.1.dist-info/DESCRIPTION.rst
beerbolaget-0.4.1.dist-info/METADATA
beerbolaget-0.4.1.dist-info/RECORD
beerbolaget-0.4.1.dist-info/WHEEL
beerbolaget-0.4.1.dist-info/metadata.json
beerbolaget-0.4.1.dist-info/top_level.txt
