Metadata-Version: 2.0
Name: beerbolaget
Version: 0.4.1
Summary: A python package to get information about the latest beer available at Systembolaget.
Home-page: https://github.com/Ceerbeerus/pybeerbolaget
Author: Robert Kallin
Author-email: kallin.roberts@gmail.com
License: UNKNOWN
Platform: UNKNOWN
Classifier: Programming Language :: Python :: 3
Classifier: License :: OSI Approved :: MIT License
Classifier: Operating System :: OS Independent
Requires-Dist: requests
